flax_vision_models/__init__.py
flax_vision_models/utils.py
flax_vision_models/vgg/__init__.py
flax_vision_models/vgg/blocks.py
flax_vision_models/vgg/build_models.py
flax_vision_models/vgg/preprocess.py
flax_vision_models/vgg/vgg16.py
flax_vision_models/vgg/vgg19.py
flax_vision_models-0.0.3.dist-info/METADATA
flax_vision_models-0.0.3.dist-info/WHEEL
flax_vision_models-0.0.3.dist-info/top_level.txt
flax_vision_models-0.0.3.dist-info/RECORD
