Metadata-Version: 2.1
Name: flax-vision-models
Version: 0.0.3
Summary: A repository of Deep Learning models in Flax
Home-page: https://github.com/soumik12345/flax-vision-models
Author: Soumik Rakshit
Author-email: 19soumik.rakshit96@gmail.com
License: UNKNOWN
Platform: UNKNOWN
Classifier: Programming Language :: Python :: 3
Classifier: Operating System :: OS Independent
Requires-Python: >=3.7.12,<3.11
Requires-Dist: jax (>=0.3.7)
Requires-Dist: flax (>=0.4.1)
Requires-Dist: clu (>=0.0.6)
Requires-Dist: wget (>=3.2)
Requires-Dist: deepdish (>=0.3.7)
Requires-Dist: wandb (>=0.12.14)
Requires-Dist: pytest (>=7.1.1)
